monacoreport/__init__.py
monacoreport/handlers.py
monacoreport/main.py
monacoreport/parser.py
monacoreport/report.py
monacoreport/report_builder.py
monacoreport-0.0.6.dist-info/licenses/LICENSE
tests/__init__.py
tests/test_handlers.py
tests/test_parser.py
tests/test_report.py
tests/test_report_builder.py
monacoreport-0.0.6.dist-info/METADATA
monacoreport-0.0.6.dist-info/WHEEL
monacoreport-0.0.6.dist-info/entry_points.txt
monacoreport-0.0.6.dist-info/top_level.txt
monacoreport-0.0.6.dist-info/RECORD
