Metadata-Version: 2.4
Name: monacoreport
Version: 0.0.6
Summary: Race report package
Author-email: Oleksandr Bohatyi <alexbogplay@gmail.com>
License-Expression: MIT
Classifier: Programming Language :: Python :: 3.13
Classifier: Operating System :: OS Independent
Requires-Python: >=3.10
License-File: LICENSE
Dynamic: license-file
